mini_six/plugins/ddt_utils.py
six_plugin_ddt_utils/__init__.py
six_plugin_ddt_utils/handler.py
six_plugin_ddt_utils-0.1.0.dist-info/LICENSE
six_plugin_ddt_utils-0.1.0.dist-info/WHEEL
six_plugin_ddt_utils-0.1.0.dist-info/METADATA
six_plugin_ddt_utils-0.1.0.dist-info/RECORD
